flask_casbin/__init__.py
flask_casbin/adapter.py
flask_casbin/config.py
flask_casbin/manager.py
flask_casbin/utils.py
flask_casbin-0.3.1.dist-info/LICENSE
flask_casbin-0.3.1.dist-info/WHEEL
flask_casbin-0.3.1.dist-info/METADATA
flask_casbin-0.3.1.dist-info/RECORD
