Metadata-Version: 2.1
Name: flask-casbin
Version: 0.3.1
Summary: Flask Casbin Integration
Home-page: https://github.com/daymien/Flask-Casbin
License: Apache-2.0
Keywords: flask,casbin,acl,rbac,abac,auth,authz,authorization,access control,permission
Author: Reimund Klain
Author-email: reimund.klain@condevtec.de
Requires-Python: >=3.6,<4.0
Classifier: Environment :: Web Environment
Classifier: Intended Audience :: Developers
Classifier: License :: OSI Approved :: Apache Software License
Classifier: Operating System :: OS Independent
Classifier: Programming Language :: Python :: 3
Classifier: Programming Language :: Python :: 3.6
Classifier: Programming Language :: Python :: 3.7
Classifier: Programming Language :: Python :: 3.8
Classifier: Programming Language :: Python :: 3.9
Classifier: Topic :: Internet :: WWW/HTTP :: Dynamic Content
Classifier: Topic :: Software Development :: Libraries :: Python Modules
Requires-Dist: casbin (>=1.1.2,<2.0.0)
Requires-Dist: flask (>=1.1,<2.0)
Project-URL: Repository, https://github.com/daymien/Flask-Casbin
